cobo_cli/__init__.py
cobo_cli/cli.py
cobo_cli/commands/__init__.py
cobo_cli/commands/app.py
cobo_cli/commands/auth.py
cobo_cli/commands/config.py
cobo_cli/commands/delete.py
cobo_cli/commands/doc.py
cobo_cli/commands/env.py
cobo_cli/commands/get.py
cobo_cli/commands/graphql.py
cobo_cli/commands/keys.py
cobo_cli/commands/login.py
cobo_cli/commands/logout.py
cobo_cli/commands/logs.py
cobo_cli/commands/open.py
cobo_cli/commands/post.py
cobo_cli/commands/put.py
cobo_cli/commands/webhook.py
cobo_cli/data/__init__.py
cobo_cli/data/auth_methods.py
cobo_cli/data/constants.py
cobo_cli/data/context.py
cobo_cli/data/environments.py
cobo_cli/data/frameworks.py
cobo_cli/data/manifest.py
cobo_cli/data/objects.py
cobo_cli/media/org_app.png
cobo_cli/tests/__init__.py
cobo_cli/tests/conftest.py
cobo_cli/tests/test_apps_commands.py
cobo_cli/tests/test_cli_integration.py
cobo_cli/tests/test_keys_commands.py
cobo_cli/tests/test_login_commands.py
cobo_cli/tests/test_utils.py
cobo_cli/utils/__init__.py
cobo_cli/utils/api.py
cobo_cli/utils/app.py
cobo_cli/utils/authorization.py
cobo_cli/utils/code_gen.py
cobo_cli/utils/config.py
cobo_cli/utils/openapi.py
cobo_cli/utils/signer.py
cobo_cli/utils/tests/test_signer.py
cobo_cli/utils/ws.py
cobo_cli-0.0.9.dist-info/LICENSE
cobo_cli-0.0.9.dist-info/METADATA
cobo_cli-0.0.9.dist-info/WHEEL
cobo_cli-0.0.9.dist-info/entry_points.txt
cobo_cli-0.0.9.dist-info/RECORD
