Metadata-Version: 2.1
Name: cobo-cli
Version: 0.0.9
Summary: Cobo Command-line Tool
License: MIT
Author: Cobo
Author-email: support@cobo.com
Requires-Python: >=3.9,<4.0
Classifier: License :: OSI Approved :: MIT License
Classifier: Programming Language :: Python :: 3
Classifier: Programming Language :: Python :: 3.9
Classifier: Programming Language :: Python :: 3.10
Classifier: Programming Language :: Python :: 3.11
Classifier: Programming Language :: Python :: 3.12
Classifier: Programming Language :: Python :: 3.13
Requires-Dist: click (>=8.1.7,<9.0.0)
Requires-Dist: dataclasses-json (>=0.6.7,<0.7.0)
Requires-Dist: email-validator (>=2.2.0,<3.0.0)
Requires-Dist: gitpython (>=3.1.43,<4.0.0)
Requires-Dist: pydantic (>=2.9.2,<3.0.0)
Requires-Dist: pydantic-settings (>=2.6.1,<3.0.0)
Requires-Dist: pynacl (>=1.5.0,<2.0.0)
Requires-Dist: python-dotenv (>=1.0.1,<2.0.0)
Requires-Dist: pyyaml (>=6.0.2,<7.0.0)
Requires-Dist: requests (>=2.32.3,<3.0.0)
Requires-Dist: tomli (>=2.0.2,<3.0.0)
Requires-Dist: tomli-w (>=1.1.0,<2.0.0)
Requires-Dist: websocket-client (>=1.8.0,<2.0.0)
